{
  "reply_markup": {
    "inline_keyboard": [
      [
        {
          "callback_data": "tt9419884",
          "text": "Doctor Strange 2"
        }
      ],
      [
        {
          "callback_data": "tt6599680",
          "text": "Doctor Strange: Strange Company (2017)"
        }
      ],
      [
        {
          "callback_data": "tt6599762",
          "text": "Doctor Strange: The Score-Cerer Supreme (2017)"
        }
      ],
      [
        {
          "callback_data": "tt1211837",
          "text": "Doctor Strange (2016)"
        }
      ],
      [
        {
          "callback_data": "tt0910865",
          "text": "Doctor Strange (2007)"
        }
      ],
      [
        {
          "callback_data": "tt0057012",
          "text": "Dr. Strangelove or: How I Learned to Stop Worrying and Love the Bomb (1964)"
        }
      ]
    ]
  }
}